algosdk/__init__.py
algosdk/__init__.pyi
algosdk/account.py
algosdk/app_access.py
algosdk/atomic_transaction_composer.py
algosdk/auction.py
algosdk/box_reference.py
algosdk/constants.py
algosdk/dryrun_results.py
algosdk/encoding.py
algosdk/error.py
algosdk/kmd.py
algosdk/logic.py
algosdk/mnemonic.py
algosdk/py.typed
algosdk/source_map.py
algosdk/transaction.py
algosdk/util.py
algosdk/wallet.py
algosdk/wordlist.py
algosdk/abi/__init__.py
algosdk/abi/address_type.py
algosdk/abi/array_dynamic_type.py
algosdk/abi/array_static_type.py
algosdk/abi/base_type.py
algosdk/abi/bool_type.py
algosdk/abi/byte_type.py
algosdk/abi/contract.py
algosdk/abi/interface.py
algosdk/abi/method.py
algosdk/abi/reference.py
algosdk/abi/string_type.py
algosdk/abi/transaction.py
algosdk/abi/tuple_type.py
algosdk/abi/ufixed_type.py
algosdk/abi/uint_type.py
algosdk/testing/__init__.py
algosdk/testing/dryrun.py
algosdk/v2client/__init__.py
algosdk/v2client/algod.py
algosdk/v2client/indexer.py
algosdk/v2client/models/__init__.py
algosdk/v2client/models/account.py
algosdk/v2client/models/account_participation.py
algosdk/v2client/models/application.py
algosdk/v2client/models/application_local_state.py
algosdk/v2client/models/application_params.py
algosdk/v2client/models/application_state_schema.py
algosdk/v2client/models/asset.py
algosdk/v2client/models/asset_holding.py
algosdk/v2client/models/asset_params.py
algosdk/v2client/models/dryrun_request.py
algosdk/v2client/models/dryrun_source.py
algosdk/v2client/models/simulate_request.py
algosdk/v2client/models/teal_key_value.py
algosdk/v2client/models/teal_value.py
py_algorand_sdk-2.11.0.dist-info/licenses/LICENSE
py_algorand_sdk-2.11.0.dist-info/METADATA
py_algorand_sdk-2.11.0.dist-info/WHEEL
py_algorand_sdk-2.11.0.dist-info/top_level.txt
py_algorand_sdk-2.11.0.dist-info/RECORD
