Metadata-Version: 2.4
Name: py-algorand-sdk
Version: 2.11.0
Summary: Algorand SDK in Python
Home-page: https://github.com/algorand/py-algorand-sdk
Author: Algorand
Author-email: pypiservice@algorand.com
License: MIT
Project-URL: Source, https://github.com/algorand/py-algorand-sdk
Requires-Python: >=3.10
License-File: LICENSE
Requires-Dist: pynacl<2,>=1.4.0
Requires-Dist: pycryptodomex<4,>=3.6.0
Requires-Dist: msgpack<2,>=1.0.0
Dynamic: author
Dynamic: author-email
Dynamic: description
Dynamic: description-content-type
Dynamic: home-page
Dynamic: license
Dynamic: license-file
Dynamic: project-url
Dynamic: requires-dist
Dynamic: requires-python
Dynamic: summary
